[
 {
  "ch": "挽",
  "py": "wǎn",
  "en": "to pull, to lead",
  "radical": "",
  "decomp": "⿰扌免",
  "hint": "hand",
  "etype": "pictophonetic",
  "need_word": true,
  "need_sentence": true
 },
 {
  "ch": "捂",
  "py": "wǔ",
  "en": "to resist",
  "radical": "",
  "decomp": "⿰扌吾",
  "hint": "To resist 吾 by hand 扌; 吾 also provides the pronunciation",
  "etype": "ideographic",
  "need_word": true,
  "need_sentence": true
 },
 {
  "ch": "捅",
  "py": "tǒng",
  "en": "to jab, to poke",
  "radical": "",
  "decomp": "⿰扌甬",
  "hint": "hand",
  "etype": "pictophonetic",
  "need_word": true,
  "need_sentence": true
 },
 {
  "ch": "捆",
  "py": "kǔn",
  "en": "to bind, to tie, to truss up",
  "radical": "",
  "decomp": "⿰扌困",
  "hint": "hand",
  "etype": "pictophonetic",
  "need_word": true,
  "need_sentence": true
 },
 {
  "ch": "捋",
  "py": "lǚ",
  "en": "to gather, to pluck",
  "radical": "",
  "decomp": "⿰扌寽",
  "hint": "To take 扌 a handful 寽; 寽 also provides the pronunciation",
  "etype": "ideographic",
  "need_word": true,
  "need_sentence": true
 },
 {
  "ch": "捌",
  "py": "bā",
  "en": "to split, to break open",
  "radical": "",
  "decomp": "⿰扌别",
  "hint": "To separate 别 by hand 扌; 别 also provides the pronunciation",
  "etype": "ideographic",
  "need_word": true,
  "need_sentence": true
 },
 {
  "ch": "捎",
  "py": "shāo",
  "en": "to carry, to take",
  "radical": "",
  "decomp": "⿰扌肖",
  "hint": "hand",
  "etype": "pictophonetic",
  "need_word": true,
  "need_sentence": true
 },
 {
  "ch": "捐",
  "py": "juān",
  "en": "to give, to donate",
  "radical": "",
  "decomp": "⿰扌肙",
  "hint": "hand",
  "etype": "pictophonetic",
  "need_word": true,
  "need_sentence": true
 },
 {
  "ch": "捕",
  "py": "bǔ",
  "en": "to arrest, to catch, to seize",
  "radical": "",
  "decomp": "⿰扌甫",
  "hint": "hand",
  "etype": "pictophonetic",
  "need_word": true,
  "need_sentence": true
 },
 {
  "ch": "损",
  "py": "sǔn",
  "en": "to damage, to harm",
  "radical": "",
  "decomp": "⿰扌员",
  "hint": "hand",
  "etype": "pictophonetic",
  "need_word": true,
  "need_sentence": true
 },
 {
  "ch": "捡",
  "py": "jiǎn",
  "en": "to pick up, to gather, to collect",
  "radical": "",
  "decomp": "⿰扌佥",
  "hint": "hand",
  "etype": "pictophonetic",
  "need_word": true,
  "need_sentence": true
 },
 {
  "ch": "捣",
  "py": "dǎo",
  "en": "to thresh, to pound",
  "radical": "",
  "decomp": "⿰扌岛",
  "hint": "hand",
  "etype": "pictophonetic",
  "need_word": true,
  "need_sentence": true
 },
 {
  "ch": "捧",
  "py": "pěng",
  "en": "to hold or offer with both hands",
  "radical": "",
  "decomp": "⿰扌奉",
  "hint": "An offering 奉 made with two hands 扌; 奉 also provides the pronunciation",
  "etype": "ideographic",
  "need_word": true,
  "need_sentence": true
 },
 {
  "ch": "据",
  "py": "jù",
  "en": "to possess, to occupy",
  "radical": "",
  "decomp": "⿰扌居",
  "hint": "hand",
  "etype": "pictophonetic",
  "need_word": true,
  "need_sentence": true
 },
 {
  "ch": "捶",
  "py": "chuí",
  "en": "to beat, to lash, to strike with a cane",
  "radical": "",
  "decomp": "⿰扌垂",
  "hint": "hand",
  "etype": "pictophonetic",
  "need_word": true,
  "need_sentence": true
 },
 {
  "ch": "捺",
  "py": "nà",
  "en": "to press down firmly with the fingers",
  "radical": "",
  "decomp": "⿰扌奈",
  "hint": "hand",
  "etype": "pictophonetic",
  "need_word": true,
  "need_sentence": true
 },
 {
  "ch": "捻",
  "py": "niǎn",
  "en": "to twist or nip with the fingers",
  "radical": "",
  "decomp": "⿰扌念",
  "hint": "hand",
  "etype": "pictophonetic",
  "need_word": true,
  "need_sentence": true
 },
 {
  "ch": "掀",
  "py": "xiān",
  "en": "to stir up",
  "radical": "",
  "decomp": "⿰扌欣",
  "hint": "hand",
  "etype": "pictophonetic",
  "need_word": true,
  "need_sentence": true
 },
 {
  "ch": "掂",
  "py": "diān",
  "en": "to heft, to weigh",
  "radical": "",
  "decomp": "⿰扌店",
  "hint": "hand",
  "etype": "pictophonetic",
  "need_word": true,
  "need_sentence": true
 },
 {
  "ch": "授",
  "py": "shòu",
  "en": "to award, to confer, to instruct, to teach",
  "radical": "",
  "decomp": "⿰扌受",
  "hint": "hand",
  "etype": "pictophonetic",
  "need_word": true,
  "need_sentence": true
 },
 {
  "ch": "掌",
  "py": "zhǎng",
  "en": "in charge",
  "radical": "",
  "decomp": "⿱尚手",
  "hint": "hand",
  "etype": "pictophonetic",
  "need_word": true,
  "need_sentence": true
 },
 {
  "ch": "掏",
  "py": "tāo",
  "en": "to take out",
  "radical": "",
  "decomp": "⿰扌匋",
  "hint": "hand",
  "etype": "pictophonetic",
  "need_word": true,
  "need_sentence": true
 },
 {
  "ch": "掐",
  "py": "qiā",
  "en": "to hold, to choke",
  "radical": "",
  "decomp": "⿰扌臽",
  "hint": "hand",
  "etype": "pictophonetic",
  "need_word": true,
  "need_sentence": true
 },
 {
  "ch": "排",
  "py": "pái",
  "en": "row, rank, file",
  "radical": "",
  "decomp": "⿰扌非",
  "hint": "hand",
  "etype": "pictophonetic",
  "need_word": true,
  "need_sentence": true
 },
 {
  "ch": "掖",
  "py": "yē",
  "en": "to tuck, to fold",
  "radical": "",
  "decomp": "⿰扌夜",
  "hint": "hand",
  "etype": "pictophonetic",
  "need_word": true,
  "need_sentence": true
 },
 {
  "ch": "掘",
  "py": "jué",
  "en": "to dig, to excavate",
  "radical": "",
  "decomp": "⿰扌屈",
  "hint": "hand",
  "etype": "pictophonetic",
  "need_word": true,
  "need_sentence": true
 },
 {
  "ch": "掠",
  "py": "lüè",
  "en": "to pillage, to ransack",
  "radical": "",
  "decomp": "⿰扌京",
  "hint": "hand",
  "etype": "pictophonetic",
  "need_word": true,
  "need_sentence": true
 },
 {
  "ch": "掣",
  "py": "chè",
  "en": "to pull, to drag",
  "radical": "",
  "decomp": "⿱制手",
  "hint": "hand",
  "etype": "pictophonetic",
  "need_word": true,
  "need_sentence": true
 },
 {
  "ch": "控",
  "py": "kòng",
  "en": "to accuse, to charge",
  "radical": "",
  "decomp": "⿰扌空",
  "hint": "hand",
  "etype": "pictophonetic",
  "need_word": true,
  "need_sentence": true
 },
 {
  "ch": "推",
  "py": "tuī",
  "en": "to push",
  "radical": "",
  "decomp": "⿰扌隹",
  "hint": "hand",
  "etype": "pictophonetic",
  "need_word": true,
  "need_sentence": true
 },
 {
  "ch": "掩",
  "py": "yǎn",
  "en": "to cover up (with a hand)",
  "radical": "",
  "decomp": "⿰扌奄",
  "hint": "hand",
  "etype": "pictophonetic",
  "need_word": true,
  "need_sentence": true
 },
 {
  "ch": "掬",
  "py": "jū",
  "en": "to grasp or hold with both hands",
  "radical": "",
  "decomp": "⿰扌匊",
  "hint": "To take 扌a handful 匊; 匊 also provides the pronunciation",
  "etype": "ideographic",
  "need_word": true,
  "need_sentence": true
 },
 {
  "ch": "掰",
  "py": "bāi",
  "en": "to rip, to tear",
  "radical": "",
  "decomp": "⿲手分手",
  "hint": "To tear something 分 with both hands 手",
  "etype": "ideographic",
  "need_word": true,
  "need_sentence": true
 },
 {
  "ch": "掴",
  "py": "guāi",
  "en": "to slap, to box one's ears",
  "radical": "",
  "decomp": "⿰扌国",
  "hint": "hand",
  "etype": "pictophonetic",
  "need_word": true,
  "need_sentence": true
 },
 {
  "ch": "掷",
  "py": "zhì",
  "en": "to throw, to hurl, to fling, to cast",
  "radical": "",
  "decomp": "⿰扌郑",
  "hint": "hand",
  "etype": "pictophonetic",
  "need_word": true,
  "need_sentence": true
 },
 {
  "ch": "掸",
  "py": "dǎn",
  "en": "to dust",
  "radical": "",
  "decomp": "⿰扌单",
  "hint": "hand",
  "etype": "pictophonetic",
  "need_word": true,
  "need_sentence": true
 },
 {
  "ch": "掺",
  "py": "càn",
  "en": "to mix, to blend, to adulterate",
  "radical": "",
  "decomp": "⿰扌参",
  "hint": "hand",
  "etype": "pictophonetic",
  "need_word": true,
  "need_sentence": true
 },
 {
  "ch": "掼",
  "py": "guàn",
  "en": "to fling, to smash",
  "radical": "",
  "decomp": "⿰扌贯",
  "hint": "hand",
  "etype": "pictophonetic",
  "need_word": true,
  "need_sentence": true
 },
 {
  "ch": "揉",
  "py": "róu",
  "en": "to massage, to knead",
  "radical": "",
  "decomp": "⿰扌柔",
  "hint": "A gentle 柔 hand 扌; 柔 also provides the pronunciation",
  "etype": "ideographic",
  "need_word": true,
  "need_sentence": true
 },
 {
  "ch": "揍",
  "py": "zòu",
  "en": "to hit, to beat",
  "radical": "",
  "decomp": "⿰扌奏",
  "hint": "hand",
  "etype": "pictophonetic",
  "need_word": true,
  "need_sentence": true
 },
 {
  "ch": "描",
  "py": "miáo",
  "en": "describe, depict",
  "radical": "扌 (提手旁)",
  "decomp": "⿰扌苗",
  "hint": "hand",
  "etype": "pictophonetic",
  "need_word": true,
  "need_sentence": true
 },
 {
  "ch": "插",
  "py": "chā",
  "en": "to insert, to stick in",
  "radical": "",
  "decomp": "⿰扌臿",
  "hint": "hand",
  "etype": "pictophonetic",
  "need_word": true,
  "need_sentence": true
 },
 {
  "ch": "揖",
  "py": "yī",
  "en": "to bow, to salute",
  "radical": "",
  "decomp": "⿰扌咠",
  "hint": "hand",
  "etype": "pictophonetic",
  "need_word": true,
  "need_sentence": true
 },
 {
  "ch": "握",
  "py": "wò",
  "en": "to grasp, to hold, to take by the hand",
  "radical": "",
  "decomp": "⿰扌屋",
  "hint": "hand",
  "etype": "pictophonetic",
  "need_word": true,
  "need_sentence": true
 },
 {
  "ch": "揣",
  "py": "chuāi",
  "en": "to stow in one's clothes",
  "radical": "",
  "decomp": "⿰扌耑",
  "hint": "hand",
  "etype": "pictophonetic",
  "need_word": true,
  "need_sentence": true
 },
 {
  "ch": "揩",
  "py": "kāi",
  "en": "to wipe, to rub, to dust, to clean",
  "radical": "",
  "decomp": "⿰扌皆",
  "hint": "hand",
  "etype": "pictophonetic",
  "need_word": true,
  "need_sentence": true
 },
 {
  "ch": "揪",
  "py": "jiū",
  "en": "to pinch, to grasp",
  "radical": "",
  "decomp": "⿰扌秋",
  "hint": "hand",
  "etype": "pictophonetic",
  "need_word": true,
  "need_sentence": true
 },
 {
  "ch": "揭",
  "py": "jiē",
  "en": "to lift off a cover",
  "radical": "",
  "decomp": "⿰扌曷",
  "hint": "hand",
  "etype": "pictophonetic",
  "need_word": true,
  "need_sentence": true
 },
 {
  "ch": "揽",
  "py": "lǎn",
  "en": "to grasp",
  "radical": "",
  "decomp": "⿰扌览",
  "hint": "hand",
  "etype": "pictophonetic",
  "need_word": true,
  "need_sentence": true
 },
 {
  "ch": "搀",
  "py": "chān",
  "en": "to mix",
  "radical": "",
  "decomp": "⿰扌⿱免⺀",
  "hint": "hand",
  "etype": "pictophonetic",
  "need_word": true,
  "need_sentence": true
 }
]