{
  "拍": {
    "origin": "The hand radical 扌 swings beside 白 (white) — picture a hand flashing as it claps.",
    "word": { "w": "拍手", "en": "to clap hands" },
    "sentence": { "cn": "大家一起拍手唱歌。", "en": "Everyone claps and sings together." }
  },
  "唯": {
    "origin": "A mouth 口 next to a little bird 隹 — one tiny voice, the only one you hear.",
    "word": { "w": "唯一", "en": "the only one" },
    "sentence": { "cn": "他是我唯一的朋友。", "en": "He is my only friend." }
  },
  "设": {
    "origin": "The speech radical 讠 means you plan and design something by talking it out first.",
    "word": { "w": "设计", "en": "to design" },
    "sentence": { "cn": "我设计了一张贺卡。", "en": "I designed a greeting card." }
  },
  "计": {
    "origin": "Speech 讠 beside ten 十 — using words and numbers to count and plan.",
    "word": { "w": "计算", "en": "to calculate" },
    "sentence": { "cn": "我们一起计算这道题。", "en": "Let's work out this problem together." }
  },
  "受": {
    "origin": "Something 冖 passed from one hand 爫 down to another 又 — you receive a gift.",
    "word": { "w": "接受", "en": "to accept" },
    "sentence": { "cn": "我高兴地接受了礼物。", "en": "I happily accepted the gift." }
  },
  "扩": {
    "origin": "The hand 扌 reaches toward 广 (wide) — your hands push something to make it bigger.",
    "word": { "w": "扩大", "en": "to enlarge" },
    "sentence": { "cn": "我们要扩大花园。", "en": "We want to make the garden bigger." }
  },
  "怀": {
    "origin": "The heart radical 忄 holds your feelings — what you carry warm against your chest.",
    "word": { "w": "怀里", "en": "in one's arms" },
    "sentence": { "cn": "小猫睡在妈妈怀里。", "en": "The kitten sleeps in mother's arms." }
  },
  "精": {
    "origin": "Rice 米 with 青 (green-fresh) — the very best, finest grain, the pure essence.",
    "word": { "w": "精彩", "en": "wonderful, splendid" },
    "sentence": { "cn": "这场表演真精彩。", "en": "This performance is really wonderful." }
  },
  "特": {
    "origin": "An ox 牛 by a temple 寺 — a special, one-of-a-kind animal that stands out.",
    "word": { "w": "特别", "en": "special" },
    "sentence": { "cn": "今天是个特别的日子。", "en": "Today is a special day." }
  },
  "赢": {
    "origin": "A character holding a shell 贝 (money) inside — gather your coins and you win!",
    "word": { "w": "赢得", "en": "to win" },
    "sentence": { "cn": "我们队赢了比赛。", "en": "Our team won the game." }
  },
  "止": {
    "origin": "A picture of a foot — when the foot plants down firmly, you stop.",
    "word": { "w": "停止", "en": "to stop" },
    "sentence": { "cn": "雨终于停止了。", "en": "The rain finally stopped." }
  },
  "典": {
    "origin": "Two hands 八 carefully holding up a precious book 冊 — a book of rules and wisdom.",
    "word": { "w": "字典", "en": "dictionary" },
    "sentence": { "cn": "我用字典查生字。", "en": "I use a dictionary to look up new words." }
  },
  "珍": {
    "origin": "The jade radical 王 marks something rare and precious — a treasure worth keeping.",
    "word": { "w": "珍惜", "en": "to cherish" },
    "sentence": { "cn": "我们要珍惜时间。", "en": "We should cherish time." }
  },
  "穷": {
    "origin": "A body squeezed under a cave 穴 using all its strength 力 — too poor to stretch out.",
    "word": { "w": "贫穷", "en": "poor, poverty" },
    "sentence": { "cn": "从前这个村子很穷。", "en": "Long ago this village was very poor." }
  },
  "留": {
    "origin": "Picture standing in a field 田, deciding to stay and remain a while longer.",
    "word": { "w": "留下", "en": "to stay, to leave behind" },
    "sentence": { "cn": "请你留下来吃饭。", "en": "Please stay and eat with us." }
  },
  "暗": {
    "origin": "The sun 日 beside a sound 音 — when the sun hides, the world turns dark.",
    "word": { "w": "黑暗", "en": "darkness" },
    "sentence": { "cn": "房间里很暗。", "en": "The room is very dark." }
  },
  "此": {
    "origin": "A foot 止 stops right here, beside 匕 — this is the very spot you mean.",
    "word": { "w": "此时", "en": "at this moment" },
    "sentence": { "cn": "此时天空下起了雪。", "en": "At this moment snow began to fall." }
  },
  "误": {
    "origin": "The speech radical 讠 — saying the wrong words leads to a mistake.",
    "word": { "w": "错误", "en": "mistake, error" },
    "sentence": { "cn": "我改正了这个错误。", "en": "I corrected this mistake." }
  },
  "性": {
    "origin": "The heart 忄 plus 生 (life) — the inborn nature and feelings you are born with.",
    "word": { "w": "性格", "en": "personality, character" },
    "sentence": { "cn": "他的性格很开朗。", "en": "His personality is very cheerful." }
  },
  "纲": {
    "origin": "Thread 纟 beside 冈 — the strong main rope that holds a whole net together.",
    "word": { "w": "提纲", "en": "outline" },
    "sentence": { "cn": "老师让我们写提纲。", "en": "The teacher asked us to write an outline." }
  },
  "部": {
    "origin": "The right-side 阝 marks a place — a section or department of something bigger.",
    "word": { "w": "部分", "en": "part, section" },
    "sentence": { "cn": "这部分我没看懂。", "en": "I didn't understand this part." }
  },
  "译": {
    "origin": "The speech radical 讠 — turning one set of words into another language.",
    "word": { "w": "翻译", "en": "to translate" },
    "sentence": { "cn": "她把故事翻译成英文。", "en": "She translated the story into English." }
  },
  "广": {
    "origin": "A lean-to roof 厂 with a dot — a wide, open building that stretches far.",
    "word": { "w": "广大", "en": "vast, wide" },
    "sentence": { "cn": "草原又广又绿。", "en": "The grassland is wide and green." }
  },
  "附": {
    "origin": "The place radical 阝 with 付 — something set down close beside, right nearby.",
    "word": { "w": "附近", "en": "nearby" },
    "sentence": { "cn": "学校附近有书店。", "en": "There is a bookstore near the school." }
  },
  "显": {
    "origin": "The sun 日 shines on top — light makes everything clear and easy to see.",
    "word": { "w": "明显", "en": "obvious, clear" },
    "sentence": { "cn": "他进步很明显。", "en": "His progress is very obvious." }
  },
  "雕": {
    "origin": "A bird 隹 beside 周 — carve carefully, as fine as a bird's tiny feathers.",
    "word": { "w": "雕刻", "en": "to carve" },
    "sentence": { "cn": "爷爷会雕刻木头。", "en": "Grandpa can carve wood." }
  },
  "复": {
    "origin": "A person 亻 who walks the same path 夂 every day 日 — doing it over again.",
    "word": { "w": "复习", "en": "to review" },
    "sentence": { "cn": "考试前要好好复习。", "en": "Review well before the exam." }
  },
  "制": {
    "origin": "A knife 刂 cutting cloth 巾 to shape — making and producing something by hand.",
    "word": { "w": "制作", "en": "to make, to produce" },
    "sentence": { "cn": "我们制作了风筝。", "en": "We made a kite." }
  },
  "基": {
    "origin": "The earth radical 土 at the bottom — solid ground that forms a strong foundation.",
    "word": { "w": "基础", "en": "foundation, basis" },
    "sentence": { "cn": "打好基础很重要。", "en": "Building a good foundation is important." }
  },
  "顶": {
    "origin": "The head radical 页 — the very top, like the crown sitting on your head.",
    "word": { "w": "顶上", "en": "on top" },
    "sentence": { "cn": "山顶上有积雪。", "en": "There is snow on the mountaintop." }
  },
  "嘴": {
    "origin": "The mouth radical 口 tells you exactly what this is — your mouth and lips.",
    "word": { "w": "嘴巴", "en": "mouth" },
    "sentence": { "cn": "他张大嘴巴笑了。", "en": "He opened his mouth wide and laughed." }
  },
  "唇": {
    "origin": "The mouth radical 口 under 辰 — the soft edges of your mouth, your lips.",
    "word": { "w": "嘴唇", "en": "lips" },
    "sentence": { "cn": "天冷时嘴唇会干。", "en": "Lips get dry when it is cold." }
  },
  "严": {
    "origin": "Think of a stern face under a firm roof 厂 — strict and serious, no joking.",
    "word": { "w": "严格", "en": "strict" },
    "sentence": { "cn": "老师对我们很严格。", "en": "The teacher is very strict with us." }
  },
  "随": {
    "origin": "Walk 辶 to the city 阝 — follow along the path wherever it leads.",
    "word": { "w": "随便", "en": "casual, as one pleases" },
    "sentence": { "cn": "你随便坐吧。", "en": "Sit wherever you like." }
  },
  "加": {
    "origin": "Strength 力 plus a mouth 口 — adding your words and power to make more.",
    "word": { "w": "加上", "en": "to add" },
    "sentence": { "cn": "二加三等于五。", "en": "Two plus three equals five." }
  },
  "呀": {
    "origin": "A mouth 口 beside 牙 (tooth) — the little sound you make when surprised: ah!",
    "word": { "w": "好呀", "en": "okay! (cheerful)" },
    "sentence": { "cn": "好呀，我们一起去！", "en": "Sure, let's go together!" }
  },
  "匹": {
    "origin": "Picture a roll of folded cloth tucked inside its wrapper — one bolt of fabric.",
    "word": { "w": "一匹马", "en": "one horse" },
    "sentence": { "cn": "草地上有一匹马。", "en": "There is a horse on the grass." }
  },
  "瓷": {
    "origin": "The tile-pottery radical 瓦 at the bottom — clay baked hard and smooth into china.",
    "word": { "w": "瓷器", "en": "porcelain, china" },
    "sentence": { "cn": "这个瓷碗很漂亮。", "en": "This porcelain bowl is very pretty." }
  },
  "众": {
    "origin": "Three people 人 stacked together — many people make a crowd.",
    "word": { "w": "众人", "en": "everyone, the crowd" },
    "sentence": { "cn": "众人都鼓起掌来。", "en": "Everyone broke into applause." }
  },
  "令": {
    "origin": "A person kneeling below a leader — receiving an order or command from above.",
    "word": { "w": "命令", "en": "order, command" },
    "sentence": { "cn": "士兵听从了命令。", "en": "The soldier obeyed the order." }
  }
}
